mechinterp/Interpreter.py
mechinterp/ModelVector.py
mechinterp/__init__.py
mechinterp/internal_utils.py
mechinterp/utils.py
mechinterp-0.0.7.dist-info/LICENSE
mechinterp-0.0.7.dist-info/METADATA
mechinterp-0.0.7.dist-info/WHEEL
mechinterp-0.0.7.dist-info/top_level.txt
mechinterp-0.0.7.dist-info/RECORD
