Metadata-Version: 2.2
Name: mechinterp
Version: 0.0.7
Summary: Library for easily using interpretability techniques in transformer models
Author-email: Yoav Gur-Arieh <yoavgurarieh@gmail.com>
License-File: LICENSE
Requires-Dist: transformer_lens
Requires-Dist: jaxtyping
Requires-Dist: torch
